{
  "events": [
    {
      "id": "e1",
      "title": "성남시 봄꽃 축제",
      "category": "행사",
      "startDate": "2026-04-05",
      "endDate": "2026-04-13",
      "location": "중앙공원",
      "target": "성남 시민 누구나",
      "summary": "화창한 봄날, 만개한 꽃들과 함께 가족, 연인과 소중한 추억을 만드세요.",
      "link": "#"
    },
    {
      "id": "e2",
      "title": "판교 청년 창업 박람회",
      "category": "행사",
      "startDate": "2026-04-19",
      "endDate": "2026-04-20",
      "location": "판교 테크노밸리",
      "target": "창업을 꿈꾸는 만 19세 ~ 39세 청년",
      "summary": "혁신적인 아이디어를 가진 청년 창업가들을 위한 교류와 성장의 장입니다.",
      "link": "#"
    },
    {
      "id": "e3",
      "title": "성남시 어린이날 큰잔치",
      "category": "행사",
      "startDate": "2026-05-05",
      "endDate": "2026-05-05",
      "location": "성남종합운동장",
      "target": "성남시 어린이 및 가족",
      "summary": "다양한 체험 프로그램과 공연으로 아이들에게 잊지 못할 하루를 선물하세요.",
      "link": "#"
    }
  ],
  "benefits": [
    {
      "id": "b1",
      "title": "성남시 청년 월세 지원금",
      "category": "혜택",
      "startDate": "2026-01-01",
      "endDate": "2026-12-31",
      "location": "온라인 신청 (성남시 홈페이지)",
      "target": "성남시 거주 만 19~34세 미취업 청년",
      "summary": "청년들의 주거비 부담을 덜어드리기 위해 월 최대 20만원을 지원합니다.",
      "link": "#"
    },
    {
      "id": "b2",
      "title": "경기도 출산지원금",
      "category": "혜택",
      "startDate": "2026-01-01",
      "endDate": "2026-12-31",
      "location": "관할 행정복지센터",
      "target": "경기도 내 출산 가정",
      "summary": "아이의 탄생을 축복하며 첫째 100만원, 둘째 150만원의 장려금을 지급합니다.",
      "link": "#"
    },
    {
      "id": "b3",
      "title": "유아학비 (누리과정) 지원",
      "category": "혜택",
      "startDate": "2023-10-27",
      "endDate": "상시",
      "location": "온라인 및 읍면동 주민센터",
      "target": "국공립 및 사립유치원에 다니는 3~5세 유아",
      "summary": "유치원에 다니는 3~5세 아동에게 유아학비, 방과후과정비 등 지원",
      "link": "https://www.gov.kr/portal/rcvfvrSvc/dtlEx/000000465790"
    },
    {
      "id": "b4",
      "title": "근로·자녀장려금",
      "category": "혜택",
      "startDate": "2023-10-27",
      "endDate": "상시",
      "location": "국세청",
      "target": "○ 신청요건을 모두 충족하는 근로소득, 사업소득 또는 종교인소득이 있는 가구로써 신청기간 내 신청하는 경우 근로소득, 사업소득 또는 종교인소득에 따라 산정한 근로장려금과 부양자녀수에 따라 산정한 자녀장려금을 지급",
      "summary": "소득과 재산이 적은 근로소득자에게 근로장려금을, 자녀가 있을 경우 자녀장려금 지급",
      "link": "https://www.gov.kr/portal/rcvfvrSvc/dtlEx/105100000001"
    },
    {
      "id": "b5",
      "title": "주택금융공사 월세자금보증",
      "category": "혜택",
      "startDate": "2023-10-27",
      "endDate": "상시",
      "location": "한국주택금융공사",
      "target": "○ 보증금 1억원 이하 및 월세금 60만원 이하인 월세 계약을 체결한 주택도시 기금 주거안정 월세대출 대상자\r\n[우대형]\r\n- 취업준비생(신청일 현재 만 35세 이하의 무소득자이며 부모 소득이 6천만원 이하인 자)\r\n- 희망키움통장 가입자\r\n- 신청일 기준 최근 1년 이내 수급사실이 인정되는 근로장려금 수급자\r\n- 취업 후 5년 이내인 사회초년생으로 신청일 현재 만 35세 이하이며 부부합산 연소득 4천만원 이하인 자\r\n- 신청일 기준 최근 1년 이내 수급사실이 인정되는 자녀장려금 수급자\r\n- 신청일 현재 주거급여 수급자 확인서가 발급되는 주거급여 수급자\r\n\r\n[일반형]\r\n- 부부합산 연소득 5천만원 이하자 중 상기 [우대형]에 해당되지 않는 자",
      "summary": "일정요건의 월세대출 대상자에게 월세자금보증을 지원",
      "link": "https://www.gov.kr/portal/rcvfvrSvc/dtlEx/116010000001"
    },
    {
      "id": "b6",
      "title": "친환경 에너지절감장비 보급",
      "category": "혜택",
      "startDate": "2023-10-27",
      "endDate": "상시",
      "location": "시·군·구청",
      "target": "어선의 기관, 고효율 등(燈)(집어등, 작업등) 외 에너지 절감 장비의 대체 또는 설치 희망하는 연근해 허가를 가진 어업인",
      "summary": "연근해 어업인을 대상으로 노후기관, 장비, 설비를 대체 보급",
      "link": "https://www.gov.kr/portal/rcvfvrSvc/dtlEx/119200000001"
    },
    {
      "id": "b7",
      "title": "해양사고 국선 심판변론인 선정 지원",
      "category": "혜택",
      "startDate": "2023-10-27",
      "endDate": "상시",
      "location": "관할지방해양안전심판원 심판관실",
      "target": "○ 사회적 약자(연령, 장애, 빈곤, 교육정도 등)에 해당하는 해양사고관련자",
      "summary": "해양사고를 입은 사회적 약자에게 국선 심판변론인 선정 및 법률자문 지원",
      "link": "https://www.gov.kr/portal/rcvfvrSvc/dtlEx/119200000007"
    },
    {
      "id": "b8",
      "title": "옵서버 승선경비 지원",
      "category": "혜택",
      "startDate": "2023-10-27",
      "endDate": "상시",
      "location": "한국수산자원공단",
      "target": "국제옵서버를 승선시킨 원양선사",
      "summary": "국제옵서버를 승선시킨 원양선사에 승선경비 및 활동 등을 지원",
      "link": "https://www.gov.kr/portal/rcvfvrSvc/dtlEx/119200000008"
    },
    {
      "id": "b9",
      "title": "합작수산물 관세 감면 추진",
      "category": "혜택",
      "startDate": "2024-07-25",
      "endDate": "상시",
      "location": "해양수산부",
      "target": "기획재정부령에서 정한 방법 또는 요건에 적합하게 채포한 수산물을 국내로 수입하는 자",
      "summary": "적법하게 채포한 수산물을 국내로 수입하는 자에게 관세감면",
      "link": "https://www.gov.kr/portal/rcvfvrSvc/dtlEx/119200000010"
    },
    {
      "id": "b10",
      "title": "귀어 창업 및 주택구입 지원(융자)",
      "category": "혜택",
      "startDate": "2023-10-27",
      "endDate": "상시",
      "location": "시·군·구청",
      "target": "○ 귀어업인(희망자 포함) 및 재촌비어업인으로서, 사업신청 연도기준 만 65세 이하인 자",
      "summary": "귀어업 지원자에 창업 및 주택구입 자금 지원 (융자 후 이자 차이를 지원)",
      "link": "https://www.gov.kr/portal/rcvfvrSvc/dtlEx/119200000012"
    }
  ],
  "lastUpdated": "2026-03-30"
}